conda_pip_hist/.pytest_cache/.gitignore
conda_pip_hist/.pytest_cache/CACHEDIR.TAG
conda_pip_hist/.pytest_cache/README.md
conda_pip_hist/.pytest_cache/v/cache/nodeids
conda_pip_hist/.pytest_cache/v/cache/stepwise
conda_pip_hist/__init__.py
conda_pip_hist/main.py
conda_pip_hist/process_env/check_file_prop.py
conda_pip_hist/process_env/conda_env_export.py
conda_pip_hist-0.3.1.dist-info/WHEEL
conda_pip_hist-0.3.1.dist-info/entry_points.txt
conda_pip_hist-0.3.1.dist-info/METADATA
conda_pip_hist-0.3.1.dist-info/RECORD
